{
  "toInsert": [
    {
      "id": "src_cl_b2f9140aa7",
      "name": "Maria Wreesmann",
      "type": "ALF",
      "source_entity": "Amber Court of Brooklyn",
      "email": "mwreesmann@ambercourtal.com",
      "phone": null
    },
    {
      "id": "src_cl_538d2dcaca",
      "name": "Brittany Cruz",
      "type": "ALF",
      "source_entity": "The Sentinel of Mohegan Lake ALP",
      "email": "bcruz@myvisitingdocs.com",
      "phone": null
    },
    {
      "id": "src_cl_638d2bff47",
      "name": "Jason King",
      "type": "ALF",
      "source_entity": "The Sentinel of Mohegan Lake ALP",
      "email": "jking@myvisitingdocs.com",
      "phone": null
    },
    {
      "id": "src_cl_1159520a5b",
      "name": "Mickey Sharma",
      "type": "ALF",
      "source_entity": "The Sentinel of Mohegan Lake ALP",
      "email": "mickey.sharma@myvisitingdoc.com",
      "phone": null
    },
    {
      "id": "src_cl_56aa96778f",
      "name": "Christina Morales",
      "type": "ALF",
      "source_entity": "Harbor View Home",
      "email": "cmorales@maximizehealth.com",
      "phone": null
    },
    {
      "id": "src_cl_48b93bcb29",
      "name": "Ashaunte Currie",
      "type": "ALF",
      "source_entity": "Harbor View Home",
      "email": "acurrie@harborviewhome.com",
      "phone": null
    },
    {
      "id": "src_cl_dda60f516f",
      "name": "Franklin Hill",
      "type": "ALF",
      "source_entity": "Harbor View Home",
      "email": "fhill@harborviewhome.com",
      "phone": null
    },
    {
      "id": "src_cl_55199e4112",
      "name": "Alcia Kirk",
      "type": "ALF",
      "source_entity": "Bronxwood Assisted Living",
      "email": "akirk@maximizehealth.com",
      "phone": null
    },
    {
      "id": "src_cl_21ac4e0933",
      "name": "Jessica Santiago",
      "type": "ALF",
      "source_entity": "Bronxwood Assisted Living",
      "email": "jsantiago@maximizehealth.com",
      "phone": null
    },
    {
      "id": "src_cl_5a42075805",
      "name": "Chantell Carter",
      "type": "ALF",
      "source_entity": "The W Assisted Living at Riverdale",
      "email": "ccarter@maximizehealth.com",
      "phone": null
    },
    {
      "id": "src_cl_191d65f0c4",
      "name": "Queenie Jackson",
      "type": "ALF",
      "source_entity": "Woodhaven Assisted Living",
      "email": "njackson@maximizehealth.com",
      "phone": null
    },
    {
      "id": "src_cl_9fe3ca0f50",
      "name": "Debra Timony",
      "type": "ALF",
      "source_entity": "Woodhaven Assisted Living",
      "email": "dtimony@woodhavenalp.com",
      "phone": null
    },
    {
      "id": "src_cl_e6e51cd5d7",
      "name": "Jana Calise",
      "type": "ALF",
      "source_entity": "Woodhaven Assisted Living",
      "email": "jcalise@woodhavenalp.com",
      "phone": null
    },
    {
      "id": "src_cl_3d51ca5304",
      "name": "Amy Walter",
      "type": "ALF",
      "source_entity": "Woodhaven Assisted Living",
      "email": "awalter@woodhavenalp.com",
      "phone": null
    },
    {
      "id": "src_cl_e6ec2d0b5f",
      "name": "Carmen Ruiz",
      "type": "ALF",
      "source_entity": "Woodhaven Assisted Living",
      "email": "cruiz@woodhavenalp.com",
      "phone": null
    },
    {
      "id": "src_cl_ca5298845b",
      "name": "Dawn Falciani",
      "type": "ALF",
      "source_entity": "Woodhaven Assisted Living",
      "email": null,
      "phone": null
    },
    {
      "id": "src_cl_bb5441c2c6",
      "name": "Batsheva Pollack",
      "type": "ALF",
      "source_entity": "Claremont Village",
      "email": "bpollack@claremontvillagealp.org",
      "phone": null
    },
    {
      "id": "src_cl_250eba4db6",
      "name": "Yoshae Woodstock",
      "type": "ALF",
      "source_entity": "Claremont Village",
      "email": "edroom@claremontvillagealp.org",
      "phone": null
    },
    {
      "id": "src_cl_53ddafa7d0",
      "name": "Judy Kessler",
      "type": "ALF",
      "source_entity": "New Fordham Arms Home Adults",
      "email": "jwkessler@thewatfordham.com",
      "phone": null
    },
    {
      "id": "src_cl_358266500a",
      "name": "Alla Hertskaya",
      "type": "ALF",
      "source_entity": "New Fordham Arms Home Adults",
      "email": "ahretskaya@thewatriverdale.com",
      "phone": null
    },
    {
      "id": "src_cl_c54ac94cd9",
      "name": "Vito Stevens",
      "type": "ALF",
      "source_entity": "Amber Court of Westbury",
      "email": "vstevens@maximizehealth.com",
      "phone": null
    },
    {
      "id": "src_cl_734f1a551a",
      "name": "Anna Zawisha",
      "type": "ALF",
      "source_entity": "Amber Court of Westbury",
      "email": "azawisha@ambercourtal.com",
      "phone": null
    },
    {
      "id": "src_cl_1c89f94ebd",
      "name": "Jaeile Williams",
      "type": "ALF",
      "source_entity": "Amber Court of Westbury",
      "email": "janwilliams@ambercourtal.com",
      "phone": null
    },
    {
      "id": "src_cl_d42d757c26",
      "name": "Brenda Beller",
      "type": "ALF",
      "source_entity": "Amber Court of Westbury",
      "email": "bbeller@ambercourtal.com",
      "phone": null
    },
    {
      "id": "src_cl_e2adda2551",
      "name": "Jessica Brugueras",
      "type": "ALF",
      "source_entity": "Amber Court of Smithtown",
      "email": "jbrugueras@ambercourtal.com",
      "phone": null
    },
    {
      "id": "src_cl_1808c3cac9",
      "name": "Sarika Desai",
      "type": "ALF",
      "source_entity": "Amber Court of Smithtown",
      "email": "sdesai@ambercourtal.com",
      "phone": null
    },
    {
      "id": "src_cl_6b0c9077db",
      "name": "Tugce Ozkir",
      "type": "ALF",
      "source_entity": "Lake Shore Assisted Living Residence",
      "email": "tozkir@ambercourtal.com",
      "phone": null
    },
    {
      "id": "src_cl_7cbc8b0913",
      "name": "Marie Beta",
      "type": "ALF",
      "source_entity": "Lake Shore Assisted Living Residence",
      "email": "ambeta@ambercourtal.com",
      "phone": null
    },
    {
      "id": "src_cl_201c7c23b3",
      "name": "Susmeet Tailor",
      "type": "ALF",
      "source_entity": "New Broadview Manor",
      "email": "susmeettailor@pymedicalgroup.com",
      "phone": null
    },
    {
      "id": "src_cl_2200b77192",
      "name": "Adam Zeitlin",
      "type": "ALF",
      "source_entity": "Brooklyn Boulevard ALP",
      "email": "dradamzeitlen@gmail.com",
      "phone": null
    },
    {
      "id": "src_cl_9cede97956",
      "name": "Brittania Waugh",
      "type": "ALF",
      "source_entity": "Castle Senior Living Assisted Living",
      "email": "bwaugh@maximizehealth.com",
      "phone": null
    },
    {
      "id": "src_cl_cc24d63529",
      "name": "Debby Ng",
      "type": "ALF",
      "source_entity": "Castle Senior Living Assisted Living",
      "email": "edebby111@aol.com",
      "phone": null
    },
    {
      "id": "src_cl_da43074d9b",
      "name": "Tamara Medinaortiz",
      "type": "ALF",
      "source_entity": "Willow Ridge of South Setauket",
      "email": "tamara.medinaortiz@willowridgseniorliving.com",
      "phone": null
    },
    {
      "id": "src_cl_c328c65aa3",
      "name": "Julie Jannotte",
      "type": "ALF",
      "source_entity": "Willow Ridge of South Setauket",
      "email": "julie.jannotte@willowridgeseniorliving.com",
      "phone": null
    },
    {
      "id": "src_cl_d7c00f9321",
      "name": "Jennifer Maldonado",
      "type": "ALF",
      "source_entity": "Willow Ridge of South Setauket",
      "email": "jennifer.maldonado@willowridgeseniorliving.com",
      "phone": null
    },
    {
      "id": "src_cl_1167146c98",
      "name": "Vernon Brown",
      "type": "ALF",
      "source_entity": "Arbors Hauppauge",
      "email": "vbrown@thearborsliving.com",
      "phone": null
    },
    {
      "id": "src_cl_8115560b4b",
      "name": "Nicholas Bailardo",
      "type": "ALF",
      "source_entity": "Arbors Hauppauge",
      "email": "nickbaialardo@pymedicalgroup.com",
      "phone": null
    },
    {
      "id": "src_cl_eb1218c62e",
      "name": "Diane Casamassina",
      "type": "ALF",
      "source_entity": "Arbors Hauppauge",
      "email": null,
      "phone": null
    },
    {
      "id": "src_cl_95f485ab83",
      "name": "Terry Thys",
      "type": "ALF",
      "source_entity": "Arbors Hauppauge",
      "email": "tthys@maximizehealth.com",
      "phone": null
    },
    {
      "id": "src_cl_0145dfd716",
      "name": "Daneille Mattera",
      "type": "ALF",
      "source_entity": "Arbors Bohemia",
      "email": "dmattera@thearborsliving.com",
      "phone": null
    },
    {
      "id": "src_cl_1b63ca24c0",
      "name": "Kerri Petitpain",
      "type": "ALF",
      "source_entity": "Arbors Bohemia",
      "email": "k.petitpain.fnp@gmail.com",
      "phone": "(631) 905-6890"
    },
    {
      "id": "src_cl_d614dfe2ef",
      "name": "Sangeetha Kamath",
      "type": "ALF",
      "source_entity": "Arbors Bohemia",
      "email": "drskamath75@gmail.com",
      "phone": null
    },
    {
      "id": "src_cl_d26f708393",
      "name": "Jacquelyn Osborne",
      "type": "ALF",
      "source_entity": "Arbors Bohemia",
      "email": "josborne@thearborsliving.com",
      "phone": null
    },
    {
      "id": "src_cl_6d3bb240f3",
      "name": "Natoya Agard",
      "type": "ALF",
      "source_entity": "The Arbors Islandia East",
      "email": "nagard@thearborsliving.com",
      "phone": null
    },
    {
      "id": "src_cl_37d95f998a",
      "name": "Cindy Lamont",
      "type": "ALF",
      "source_entity": "The Arbors Islandia East",
      "email": "clamont@thearborsliving.com",
      "phone": null
    },
    {
      "id": "src_cl_62486dc8c5",
      "name": "Melissa Orlando",
      "type": "ALF",
      "source_entity": "The Arbors Islandia East",
      "email": "morlando@thearborsliving.com",
      "phone": null
    },
    {
      "id": "src_cl_dd1b2e11eb",
      "name": "Mariana Costa",
      "type": "ALF",
      "source_entity": "The Arbors Islandia East",
      "email": "mcosta@maximizehealth.com",
      "phone": null
    },
    {
      "id": "src_cl_7a8205c2b7",
      "name": "Alison Menze",
      "type": "ALF",
      "source_entity": "The Arbors Islandia East",
      "email": "amenze@thearborsliving.com",
      "phone": null
    },
    {
      "id": "src_cl_ef8441e2a3",
      "name": "Tawanda Booker",
      "type": "ALF",
      "source_entity": "The Arbors Islandia East",
      "email": "tbooker@thearborsliving.com",
      "phone": null
    },
    {
      "id": "src_cl_31d510c622",
      "name": "Traci Battle",
      "type": "ALF",
      "source_entity": "The Arbors Islandia East",
      "email": "tbattle@thearborsliving.com",
      "phone": null
    },
    {
      "id": "src_cl_69607cc019",
      "name": "Laura Berry",
      "type": "ALF",
      "source_entity": "The Arbors Islandia West",
      "email": "lberry@thearborsliving.com",
      "phone": null
    },
    {
      "id": "src_cl_4fbb1da3d7",
      "name": "Natia Nasareia",
      "type": "ALF",
      "source_entity": "Arbors Westbury",
      "email": "nnasareia@thearborsliving.com",
      "phone": null
    },
    {
      "id": "src_cl_11234eea21",
      "name": "Aaliyah Arocho",
      "type": "ALF",
      "source_entity": "Arbors Westbury",
      "email": "aarocho@maximizehealth.com",
      "phone": null
    },
    {
      "id": "src_cl_ba1a23871c",
      "name": "Suzanne Lee",
      "type": "ALF",
      "source_entity": "Arbors Westbury",
      "email": "suzannelee@pymedicalgroup.com",
      "phone": null
    },
    {
      "id": "src_cl_2a53c7a395",
      "name": "Carla Hoene",
      "type": "ALF",
      "source_entity": "Arbors Westbury",
      "email": "choene@thearborsliving.com",
      "phone": null
    },
    {
      "id": "src_cl_187cc24770",
      "name": "Sabine Fednard",
      "type": "ALF",
      "source_entity": "Arbors Westbury",
      "email": "sfednard@pymedicalgroup.com",
      "phone": null
    },
    {
      "id": "src_cl_73f5b06877",
      "name": "Meghan Alvarez",
      "type": "ALF",
      "source_entity": "Arbors Westbury",
      "email": "malvarez@thearborsliving.com",
      "phone": null
    },
    {
      "id": "src_cl_6b2a01f567",
      "name": "Winnie Rutherford",
      "type": "ALF",
      "source_entity": "Braemar Living",
      "email": "wrutherford@braemarliving.com",
      "phone": null
    },
    {
      "id": "src_cl_1c13d06382",
      "name": "Faith Quesada",
      "type": "ALF",
      "source_entity": "New Haven Manor",
      "email": "fquesada@thewatnewhaven.com",
      "phone": null
    },
    {
      "id": "src_cl_e08b7c256d",
      "name": "Kaitlyn Folchetti",
      "type": "ALF",
      "source_entity": "The Plaza at Clover Lake",
      "email": "kfolchetti@cloverlakeliving.com",
      "phone": null
    },
    {
      "id": "src_cl_4df315c8b5",
      "name": "Batsheva Schoenfeld",
      "type": "ALF",
      "source_entity": "The Plaza at Clover Lake",
      "email": null,
      "phone": null
    },
    {
      "id": "src_cl_49954c94df",
      "name": "Meriem Khalid",
      "type": "ALF",
      "source_entity": "The Plaza at Clover Lake",
      "email": "mkhalid@maximizehealth.com",
      "phone": null
    },
    {
      "id": "src_cl_3c4fae4af5",
      "name": "Samara Lawes",
      "type": "ALF",
      "source_entity": "The Eliot at New Rochelle",
      "email": "slawes@myvisitingdocs.com",
      "phone": null
    },
    {
      "id": "src_cl_750d285938",
      "name": "Linda Osborne",
      "type": "ALF",
      "source_entity": "The Eliot at New Rochelle",
      "email": "losborne@eliotalp.com",
      "phone": null
    },
    {
      "id": "src_cl_52671c5853",
      "name": "Maxine Cardwell",
      "type": "ALF",
      "source_entity": "The Eliot at New Rochelle",
      "email": "mcardwell@eliotalp.com",
      "phone": null
    },
    {
      "id": "src_cl_deb167175a",
      "name": "Kim Stahl",
      "type": "ALF",
      "source_entity": "Bayview Rest Home",
      "email": "kstahl@thewatbayview.com",
      "phone": null
    }
  ],
  "toSkipDup": [],
  "skipped": [
    {
      "row": 0,
      "reason": "single name, no email last (Addo)",
      "facility": "ACB",
      "name": "Dr. Addo",
      "email": "addoyobs@gmail.com"
    },
    {
      "row": 2,
      "reason": "single name, no email last (Bustillos)",
      "facility": "ACPG",
      "name": "Y. Bustillos , Medical Assist",
      "email": "ybustillos@maximizehealth.com + support@max"
    },
    {
      "row": 9,
      "reason": "empty",
      "facility": "Bronxwood"
    },
    {
      "row": 27,
      "reason": "single name, no email last (Manisha)",
      "facility": "ACS",
      "name": "Manisha, Medical Assist",
      "email": "Masmithtown@ambercourtal.com + support@max"
    },
    {
      "row": 30,
      "reason": "empty/non-person row",
      "facility": "Lakeshore",
      "name": "Medical Assistant",
      "email": "malakeshore@ambercourtal.com"
    },
    {
      "row": 33,
      "reason": "support-only email",
      "facility": "Lakeshore"
    },
    {
      "row": 35,
      "reason": "empty",
      "facility": "Brooklyn ALP"
    },
    {
      "row": 37,
      "reason": "support-only email",
      "facility": "Castle"
    },
    {
      "row": 40,
      "reason": "single name, no email last (Jennifer)",
      "facility": "Brichwood",
      "name": "Jennifer, Case mgr",
      "email": "Jennifer@suttongardensseniorliving.com"
    },
    {
      "row": 44,
      "reason": "empty/non-person row",
      "facility": "Arbors Haupaugge",
      "name": "",
      "email": "vbrown@thearborsliving.com"
    },
    {
      "row": 50,
      "reason": "empty/non-person row",
      "facility": "Arbors Bohemia",
      "name": "MA Maximize",
      "email": ""
    },
    {
      "row": 53,
      "reason": "empty",
      "facility": "Arbors Bohemia"
    },
    {
      "row": 56,
      "reason": "could not resolve (S Russell OLD assistant Admin)",
      "facility": "Arbors Islandia East",
      "name": "S Russell OLD assistant Admin",
      "email": "srussell@thearborsliving.com"
    },
    {
      "row": 60,
      "reason": "duplicate person",
      "name": "Nicholas Bailardo",
      "facility": "Arbors Islandia East"
    },
    {
      "row": 61,
      "reason": "duplicate person",
      "name": "Terry Thys",
      "facility": "Arbors Islandia East"
    },
    {
      "row": 64,
      "reason": "duplicate person",
      "name": "Cindy Lamont",
      "facility": "Islandia East Safercare"
    },
    {
      "row": 67,
      "reason": "duplicate person",
      "name": "Mariana Costa",
      "facility": "Arbors Islandia West"
    },
    {
      "row": 68,
      "reason": "duplicate person",
      "name": "Cindy Lamont",
      "facility": "Arbors Islandia West"
    },
    {
      "row": 69,
      "reason": "duplicate person",
      "name": "Alison Menze",
      "facility": "Arbors Islandia West"
    },
    {
      "row": 70,
      "reason": "duplicate person",
      "name": "Nicholas Bailardo",
      "facility": "Arbors Islandia West"
    },
    {
      "row": 71,
      "reason": "duplicate person",
      "name": "Terry Thys",
      "facility": "Arbors Islandia West"
    },
    {
      "row": 78,
      "reason": "duplicate person",
      "name": "Sangeetha Kamath",
      "facility": "Arbors Westbury"
    },
    {
      "row": 80,
      "reason": "empty/non-person row",
      "facility": "New Haven Manor",
      "name": "Medical Assist",
      "email": ""
    },
    {
      "row": 82,
      "reason": "support-only email",
      "facility": "The Plaza at Clover Lake"
    },
    {
      "row": 86,
      "reason": "duplicate person",
      "name": "Jason King",
      "facility": "Eliot New Rochelle"
    },
    {
      "row": 90,
      "reason": "duplicate person",
      "name": "Adam Zeitlin",
      "facility": "Blvd Alp Queens"
    },
    {
      "row": 92,
      "reason": "empty",
      "facility": "Bayview"
    },
    {
      "row": 93,
      "reason": "empty",
      "facility": "Bayview"
    },
    {
      "row": 94,
      "reason": "empty",
      "facility": "Bayview"
    },
    {
      "row": 95,
      "reason": "empty",
      "facility": "Bayview"
    },
    {
      "row": 96,
      "reason": "empty",
      "facility": "Bayview"
    },
    {
      "row": 97,
      "reason": "empty",
      "facility": "Bayview"
    },
    {
      "row": 98,
      "reason": "empty",
      "facility": "Bayview"
    },
    {
      "row": 99,
      "reason": "empty",
      "facility": "Bayview"
    },
    {
      "row": 100,
      "reason": "empty",
      "facility": "Bayview"
    },
    {
      "row": 101,
      "reason": "empty",
      "facility": "Bayview"
    },
    {
      "row": 102,
      "reason": "empty",
      "facility": "Bayview"
    },
    {
      "row": 103,
      "reason": "empty",
      "facility": "Bayview"
    },
    {
      "row": 104,
      "reason": "empty",
      "facility": "Bayview"
    },
    {
      "row": 105,
      "reason": "empty",
      "facility": "Bayview"
    },
    {
      "row": 106,
      "reason": "empty",
      "facility": "Bayview"
    },
    {
      "row": 107,
      "reason": "empty",
      "facility": "Bayview"
    },
    {
      "row": 108,
      "reason": "empty",
      "facility": "Bayview"
    },
    {
      "row": 109,
      "reason": "empty",
      "facility": "Bayview"
    }
  ]
}